README.md
requirements.txt
setup.py
grui/__init__.py
grui/app.py
grui/decorator.py
grui/service.py
grui/sql_database.py
grui/typing.py
grui/utils.py
grui.egg-info/PKG-INFO
grui.egg-info/SOURCES.txt
grui.egg-info/dependency_links.txt
grui.egg-info/requires.txt
grui.egg-info/top_level.txt